setup.py
cloudpy/__init__.py
cloudpy/cloudpy_agent.py
cloudpy/cloudpy_clean.py
cloudpy/cloudpy_config.py
cloudpy/cloudpy_deps.py
cloudpy/cloudpy_files.py
cloudpy/cloudpy_main.py
cloudpy/cloudpy_package.py
cloudpy/cloudpy_run.py
cloudpy/cloudpy_struct.py
cloudpy/cloudpy_sync.py
cloudpy.egg-info/PKG-INFO
cloudpy.egg-info/SOURCES.txt
cloudpy.egg-info/dependency_links.txt
cloudpy.egg-info/entry_points.txt
cloudpy.egg-info/requires.txt
cloudpy.egg-info/top_level.txt