Metadata-Version: 1.0
Name: cloudpy
Version: 0.3.11
Summary: Run Python Scripts in virtual environment on an remote host
Home-page: https://github.com/Tefx/cloudpy
Author: Zhu Zhaomeng
Author-email: zhaomeng.zhu@gmail.com
License: UNKNOWN
Platform: UNKNOWN
Classifier: Development Status :: 3 - Alpha
Classifier: Environment :: Console
Classifier: Intended Audience :: Developers
Classifier: License :: OSI Approved :: GNU Library or Lesser General Public License (LGPL)
Classifier: Topic :: Utilities
